tobiiglasses/__init__.py
tobiiglasses/entities.py
tobiiglasses/events.py
tobiiglasses/exporter.py
tobiiglasses/gazedata.py
tobiiglasses/livedata.py
tobiiglasses/livedatajson.py
tobiiglasses/metrics.py
tobiiglasses/recordings.py
tobiiglasses/segments.py
tobiiglasses/utils.py
tobiiglasses/video.py
tobiiglasses/aoi/__init__.py
tobiiglasses/aoi/clustering.py
tobiiglasses/aoi/heatmaps.py
tobiiglasses/aoi/model.py
tobiiglasses/aoi/surf.py
tobiiglasses/aoi/aruco/__init__.py
tobiiglasses/aoi/aruco/model.py
tobiiglasses/aoi/dnn/__init__.py
tobiiglasses/aoi/dnn/faces/__init__.py
tobiiglasses/aoi/dnn/faces/model.py
tobiiglasses/filters/__init__.py
tobiiglasses/filters/df.py
tobiiglasses/filters/fixations.py
tobiiglasses/filters/models.py
tobiiglasses-1.1.dist-info/LICENSE
tobiiglasses-1.1.dist-info/METADATA
tobiiglasses-1.1.dist-info/WHEEL
tobiiglasses-1.1.dist-info/top_level.txt
tobiiglasses-1.1.dist-info/RECORD
